deepa2/__init__.py
deepa2/builder/__init__.py
deepa2/builder/aifdb_builder.py
deepa2/builder/arg_kp_builder.py
deepa2/builder/arg_q_builder.py
deepa2/builder/core.py
deepa2/builder/entailmentbank_builder.py
deepa2/builder/jinjafilters.py
deepa2/builder/nli_builder.py
deepa2/builder/pipeline.py
deepa2/builder/utils.py
deepa2/config.py
deepa2/datastructures.py
deepa2/main.py
deepa2/metrics/__init__.py
deepa2/metrics/metric_handler.py
deepa2/parsers.py
deepa2/preptrain/__init__.py
deepa2/preptrain/t2tpreprocessor.py
deepa2/testing/__init__.py
deepa2/testing/buildertester.py
deepa2-0.1.16.dist-info/entry_points.txt
deepa2-0.1.16.dist-info/LICENSE
deepa2-0.1.16.dist-info/WHEEL
deepa2-0.1.16.dist-info/METADATA
deepa2-0.1.16.dist-info/RECORD
