Metadata-Version: 2.1
Name: deepa2
Version: 0.1.16
Summary: Cast NLP data as multiangular DeepA2 datasets and integrate these in training pipeline
Home-page: https://github.com/debatelab/deepa2
License: Apache-2.0
Author: Gregor Betz
Author-email: gregor.betz@kit.edu
Requires-Python: >=3.7.1,<3.11
Classifier: License :: OSI Approved :: Apache Software License
Classifier: Programming Language :: Python :: 3
Classifier: Programming Language :: Python :: 3.8
Classifier: Programming Language :: Python :: 3.9
Classifier: Programming Language :: Python :: 3.10
Requires-Dist: Jinja2 (>=3.0.3,<4.0.0)
Requires-Dist: datasets (>=2.8.0,<3.0.0)
Requires-Dist: editdistance (>=0.6.0,<0.7.0)
Requires-Dist: networkx (>=2.6.3,<3.0.0)
Requires-Dist: nltk (>=3.7,<4.0)
Requires-Dist: numpy (==1.21.5)
Requires-Dist: pandas (==1.3.5)
Requires-Dist: pyarrow (>=6.0.1,<7.0.0)
Requires-Dist: requests (>=2.27.1,<3.0.0)
Requires-Dist: sacrebleu (>=2.1.0,<3.0.0)
Requires-Dist: ttp (>=0.8.4,<0.9.0)
Requires-Dist: typer[all] (>=0.4.0,<0.5.0)
